{
  "$schema": "https://mintlify.com/docs.json",
  "name": "Baklog",
  "theme": "almond",
  "colors": {
    "primary": "#38bdf8",
    "light": "#38bdf8",
    "dark": "#38bdf8"
  },
  "favicon": "https://media.brand.dev/51a076ca-bc0a-40f1-81df-4e3ccfd74217.svg",
  "navbar": {
    "primary": {
      "type": "github",
      "href": "https://github.com/Ogrods/BAKLOG"
    }
  },
  "footer": {
    "socials": {
      "github": "https://github.com/Ogrods/BAKLOG"
    }
  },
  "navigation": {
    "tabs": [
      {
        "tab": "Documentation",
        "groups": [
          {
            "group": "Get Started",
            "pages": [
              "introduction",
              "getting-started",
              "connecting-stores"
            ]
          },
          {
            "group": "Using Baklog",
            "pages": [
              "dashboard",
              "library-and-wishlist",
              "refresh-and-enrichment",
              "profiles-and-moving"
            ]
          },
          {
            "group": "Reference",
            "pages": [
              "fetcher-reference",
              "configuration",
              "privacy-and-security"
            ]
          },
          {
            "group": "Help",
            "pages": [
              "troubleshooting",
              "faq",
              "getting-help"
            ]
          }
        ]
      }
    ]
  }
}
